pytorch_toolbelt/__init__.py
pytorch_toolbelt/datasets/__init__.py
pytorch_toolbelt/datasets/common.py
pytorch_toolbelt/datasets/mean_std.py
pytorch_toolbelt/datasets/segmentation.py
pytorch_toolbelt/datasets/wrappers.py
pytorch_toolbelt/inference/__init__.py
pytorch_toolbelt/inference/ensembling.py
pytorch_toolbelt/inference/functional.py
pytorch_toolbelt/inference/tiles.py
pytorch_toolbelt/inference/tiles_3d.py
pytorch_toolbelt/inference/tta.py
pytorch_toolbelt/losses/__init__.py
pytorch_toolbelt/losses/balanced_bce.py
pytorch_toolbelt/losses/bitempered_loss.py
pytorch_toolbelt/losses/dice.py
pytorch_toolbelt/losses/focal.py
pytorch_toolbelt/losses/focal_cosine.py
pytorch_toolbelt/losses/functional.py
pytorch_toolbelt/losses/jaccard.py
pytorch_toolbelt/losses/logcosh.py
pytorch_toolbelt/losses/lovasz.py
pytorch_toolbelt/losses/quality_focal_loss.py
pytorch_toolbelt/losses/soft_bce.py
pytorch_toolbelt/losses/soft_ce.py
pytorch_toolbelt/losses/soft_f1.py
pytorch_toolbelt/losses/wing_loss.py
pytorch_toolbelt/modules/__init__.py
pytorch_toolbelt/modules/activations.py
pytorch_toolbelt/modules/coord_conv.py
pytorch_toolbelt/modules/drop_path.py
pytorch_toolbelt/modules/dropblock.py
pytorch_toolbelt/modules/dsconv.py
pytorch_toolbelt/modules/fpn.py
pytorch_toolbelt/modules/identity.py
pytorch_toolbelt/modules/initialization.py
pytorch_toolbelt/modules/interfaces.py
pytorch_toolbelt/modules/normalization.py
pytorch_toolbelt/modules/ocnet.py
pytorch_toolbelt/modules/pooling.py
pytorch_toolbelt/modules/scse.py
pytorch_toolbelt/modules/simple.py
pytorch_toolbelt/modules/spp.py
pytorch_toolbelt/modules/srm.py
pytorch_toolbelt/modules/unet.py
pytorch_toolbelt/modules/upsample.py
pytorch_toolbelt/modules/backbone/__init__.py
pytorch_toolbelt/modules/backbone/inceptionv4.py
pytorch_toolbelt/modules/backbone/mobilenet.py
pytorch_toolbelt/modules/backbone/senet.py
pytorch_toolbelt/modules/backbone/wider_resnet.py
pytorch_toolbelt/modules/decoders/__init__.py
pytorch_toolbelt-0.8.0.dist-info/LICENSE
pytorch_toolbelt-0.8.0.dist-info/METADATA
pytorch_toolbelt-0.8.0.dist-info/WHEEL
pytorch_toolbelt-0.8.0.dist-info/top_level.txt
pytorch_toolbelt-0.8.0.dist-info/RECORD
