Metadata-Version: 2.1
Name: pytorch_toolbelt
Version: 0.8.0
Summary: PyTorch extensions for fast R&D prototyping and Kaggle farming
Home-page: https://github.com/BloodAxe/pytorch-toolbelt
Author: Eugene Khvedchenya
Author-email: ekhvedchenya@gmail.com
License: License :: OSI Approved :: MIT License
Keywords: PyTorch,Kaggle,Deep Learning,Machine Learning,ResNet,VGG,ResNext,Unet,Focal,FPN,EfficientNet,Test-Time Augmentation,Model Ensembling,Model Surgery
Classifier: Development Status :: 4 - Beta
Classifier: Intended Audience :: Developers
Classifier: Intended Audience :: Science/Research
Classifier: Programming Language :: Python
Classifier: Programming Language :: Python :: 3
Classifier: Programming Language :: Python :: 3.8
Classifier: Programming Language :: Python :: 3.9
Classifier: Programming Language :: Python :: 3.10
Classifier: Programming Language :: Python :: 3.11
Classifier: Operating System :: OS Independent
Classifier: Topic :: Scientific/Engineering :: Mathematics
Classifier: Topic :: Scientific/Engineering :: Image Recognition
Classifier: Topic :: Scientific/Engineering :: Artificial Intelligence
Classifier: Topic :: Software Development :: Libraries
Classifier: Topic :: Software Development :: Libraries :: Python Modules
Classifier: Topic :: Software Development :: Libraries :: Application Frameworks
Requires-Python: >=3.8.0
License-File: LICENSE
Requires-Dist: torch >=1.11.0
Requires-Dist: torchvision
Requires-Dist: scipy >=1.4.0
Requires-Dist: opencv-python >=4.1
Provides-Extra: tests
Requires-Dist: pytest ; extra == 'tests'
Requires-Dist: black ==23.3.0 ; extra == 'tests'
Requires-Dist: timm ==0.6.7 ; extra == 'tests'
Requires-Dist: matplotlib ; extra == 'tests'
